{"cameraMode":{"drawMode":0,"name":"Shaded","section":"Shading Mode"},"sceneLighting":false,"audioPlay":false,"sceneViewState":{"m_AlwaysRefresh":false,"showFog":true,"showSkybox":false,"showFlares":true,"showImageEffects":true,"showParticleSystems":true,"showVisualEffectGraphs":true,"m_FxEnabled":true},"in2DMode":false,"pivot":{"x":-9.47966194152832,"y":10.080567359924317,"z":-0.9310116767883301},"rotation":{"x":-0.14166902005672456,"y":-0.8569737076759338,"z":0.32134711742401125,"w":-0.3774048388004303},"size":6.065673828125,"orthographic":false}