{"cameraMode":{"drawMode":0,"name":"Shaded","section":"Shading Mode"},"sceneLighting":true,"audioPlay":false,"sceneViewState":{"m_AlwaysRefresh":false,"showFog":true,"showSkybox":true,"showFlares":true,"showImageEffects":true,"showParticleSystems":true,"showVisualEffectGraphs":true,"m_FxEnabled":true},"in2DMode":false,"pivot":{"x":-59.98835754394531,"y":-129.54356384277345,"z":74.89759063720703},"rotation":{"x":0.298147588968277,"y":-0.4795379638671875,"z":0.17746536433696748,"w":0.8060978651046753},"size":161.65679931640626,"orthographic":false}